STPyV8.py
_STPyV8.cpython-314-darwin.so
stpyv8-icu/icudtl.dat
stpyv8-13.1.201.22.dist-info/RECORD
stpyv8-13.1.201.22.dist-info/WHEEL
stpyv8-13.1.201.22.dist-info/top_level.txt
stpyv8-13.1.201.22.dist-info/METADATA
stpyv8-13.1.201.22.dist-info/licenses/LICENSE.txt
stpyv8.dylibs/libboost_iostreams.dylib
stpyv8.dylibs/libboost_graph.dylib
stpyv8.dylibs/libboost_container.dylib
stpyv8.dylibs/libboost_random.dylib
stpyv8.dylibs/libboost_python314.dylib
stpyv8.dylibs/libboost_regex.dylib
stpyv8.dylibs/libboost_filesystem.dylib
stpyv8.dylibs/liblzma.5.dylib
stpyv8.dylibs/libboost_atomic.dylib
stpyv8.dylibs/libboost_system.dylib
stpyv8.dylibs/libzstd.1.5.7.dylib
